[1,0,0,[["cc.JsonAsset",["_name","json"],1]],[[0,0,1,3]],[[0,"maps_config",{"maps":[{"id":"map","name":"web3_city","prefabPath":"scene/classic_map","previewImagePath":"images/maps/default_preview","type":"classic"},{"id":"crypto_island","name":"加密岛屿(未开放)","prefabPath":"scene/crypto_island","previewImagePath":"images/maps/crypto_island","type":"brawl"},{"id":"defi_plaza","name":"DeFi广场(未开放)","prefabPath":"scene/defi_plaza","previewImagePath":"images/maps/defi_plaza","type":"classic"}]}]],0,0,[],[],[]]
